mkdocs_exclude_unused_files/__init__.py
mkdocs_exclude_unused_files/plugin.py
mkdocs_exclude_unused_files-1.4.1.dist-info/LICENSE.md
mkdocs_exclude_unused_files-1.4.1.dist-info/METADATA
mkdocs_exclude_unused_files-1.4.1.dist-info/WHEEL
mkdocs_exclude_unused_files-1.4.1.dist-info/entry_points.txt
mkdocs_exclude_unused_files-1.4.1.dist-info/RECORD
