Metadata-Version: 2.3
Name: mkdocs-exclude-unused-files
Version: 1.4.1
Summary: A mkdocs plugin that excludes assets that are unused (orphaned) from being included in the final mkdocs output.
License: MIT
Keywords: mkdocs,mkdocs-plugin,unused-files,orphaned-files
Author: Jonas Lorenz
Author-email: jonas@jonasdoesthings.com
Requires-Python: >=3.8.1,<4.0
Classifier: License :: OSI Approved :: MIT License
Classifier: Programming Language :: Python :: 3
Classifier: Programming Language :: Python :: 3.9
Classifier: Programming Language :: Python :: 3.10
Classifier: Programming Language :: Python :: 3.11
Classifier: Programming Language :: Python :: 3.12
Classifier: Programming Language :: Python :: 3.13
Requires-Dist: beautifulsoup4 (>=4.12.3,<5.0.0)
Requires-Dist: mkdocs (>=1.5.3,<2.0.0)
Project-URL: Documentation, https://github.com/JonasDoesThings/mkdocs-exclude-unused-files/blob/main/README.md
Project-URL: Homepage, https://github.com/JonasDoesThings/mkdocs-exclude-unused-files
Project-URL: History, https://github.com/JonasDoesThings/mkdocs-exclude-unused-files/releases
Project-URL: Issues, https://github.com/JonasDoesThings/mkdocs-exclude-unused-files/issues
Project-URL: Repository, https://github.com/JonasDoesThings/mkdocs-exclude-unused-files
